tdasha/__init__.py
tdasha/compute.py
tdasha/io.py
tdasha/window.py
tdasha-0.2.3.dist-info/LICENSE
tdasha-0.2.3.dist-info/WHEEL
tdasha-0.2.3.dist-info/METADATA
tdasha-0.2.3.dist-info/RECORD
